gen10/__init__.py
gen10/_version.py
gen10/advanced.py
gen10/advanced_cat.py
gen10/advanced_deu.py
gen10/advanced_esp.py
gen10/basics.py
gen10/cat_basics.py
gen10/deu_basics.py
gen10/esp_basics.py
gen10-1.4.3.dist-info/licenses/LICENSE
tests/__init__.py
tests/test_advanced.py
tests/test_functions.py
gen10-1.4.3.dist-info/METADATA
gen10-1.4.3.dist-info/WHEEL
gen10-1.4.3.dist-info/top_level.txt
gen10-1.4.3.dist-info/RECORD
