Metadata-Version: 2.4
Name: gen10
Version: 1.4.3
Summary: Package for genetics and genomics related functions, mainly for educational purposes.
Home-page: https://github.com/joanalnu/gen10
Author: Joan Alcaide-Núñez
Author-email: joanalnu@outlook.com
Classifier: Programming Language :: Python :: 3
Classifier: License :: OSI Approved :: MIT License
Classifier: Operating System :: Unix
Requires-Python: >=3.9
License-File: LICENSE
Requires-Dist: pandas
Requires-Dist: requests
Requires-Dist: biopython
Requires-Dist: matplotlib
Requires-Dist: pytest
Dynamic: author
Dynamic: author-email
Dynamic: classifier
Dynamic: description
Dynamic: description-content-type
Dynamic: home-page
Dynamic: license-file
Dynamic: requires-dist
Dynamic: requires-python
Dynamic: summary
